kgraphgen/__init__.py
kgraphgen-0.0.1.dist-info/LICENSE
kgraphgen-0.0.1.dist-info/METADATA
kgraphgen-0.0.1.dist-info/WHEEL
kgraphgen-0.0.1.dist-info/top_level.txt
kgraphgen-0.0.1.dist-info/RECORD
